water_column_sonar_resampling-25.11.2.dist-info/licenses/LICENSE
wrc_workspace/__init__.py
wrc_workspace/dev.py
wrc_workspace/water_column_resampling.py
water_column_sonar_resampling-25.11.2.dist-info/METADATA
water_column_sonar_resampling-25.11.2.dist-info/WHEEL
water_column_sonar_resampling-25.11.2.dist-info/top_level.txt
water_column_sonar_resampling-25.11.2.dist-info/RECORD
