Metadata-Version: 2.4
Name: water-column-sonar-resampling
Version: 25.11.2
Summary: Water Column Sonar Data Reprocessing Project for Warren Tech Capstone 2026
Author-email: Caitlyn Nguyen <cpnguyen0000@gmail.com>, Logan Lessen <loganlessen@gmail.com>
Maintainer-email: Caitlyn Nguyen <cpnguyen0000@gmail.com>, Logan Lessen <loganlessen@gmail.com>
License-Expression: MIT
Keywords: reprocessing,sonar,water column,zarr
Requires-Python: >=3.12
License-File: LICENSE
Requires-Dist: dask[array]>=2025.9.1
Requires-Dist: matplotlib>=3.10.6
Requires-Dist: numcodecs>=0.16.2
Requires-Dist: numpy>=2.3.3
Requires-Dist: pandas>=2.3.2
Requires-Dist: s3fs>=2025.9.0
Requires-Dist: scipy>=1.16.2
Requires-Dist: tqdm>=4.67.1
Requires-Dist: xarray[complete]>=2025.9.0
Requires-Dist: zarr>=3.1.2
Provides-Extra: dev
Requires-Dist: pytest>=8.4.2; extra == "dev"
Dynamic: license-file
